Workbook

Sheet COVER
A1: DD FORM 1391 COST ESTIMATE
A3: Building | B3: SCH-3270
A4: iNFADS Description | B4: AUTO ORGANIZATIONAL SHOP CAB
A5: Primary CCN | B5: 21451
A6: RPUID | B6: 1174058
A7: PAX ID | B7: 387568
A8: Fi Web Project Number | B8: BU26PPE74M
A9: Installation/UIC | B9: M67400 (SH)
A10: Location | B10: MARINE CORPS BASE, CAMP SMEDLEY BUTLER (CAMP SCHWAB-6009), HENOKO OKINAWA, JAPAN
A11: Project Title | B11: Repair Bldg. 3270
A12: Fund Type | B12: O&MMC
A13: Acquisition Method | B13: Design-Build (DB)
A14: Total Building GSF (iNFADS) | B14: 25390
A15: PRV (iNFADS) | B15: 39507617
A16: LSH (2.5% of PRV) | B16: 987690
A17: Locked Total Project Cost ($) | B17: 3527753
A18: Locked TPC ($000, printed) | B18: 3528
A19: Prepared By | B19: Anthony L. Potter, Facilities Planner, MCIPAC G-F PPE
A20: Signing Officer (PWO) | B20: CDR Justus K. O'Connor
A21: Government Client | B21: Bil Hawkins, P.E., PMP, Deputy PWO
A22: Reviewer | B22: Robert W. Kaye, RA, Planning Director NAVFAC FEAD

Sheet BLOCK9
A1: 9. Cost Estimates
A3: Item | B3: UM | C3: Quantity | D3: Unit Cost | E3: Cost ($000)
A4: PRIMARY FACILITY | E4: =BACKUP!B13
A5: AUTO ORGANIZATIONAL SHOP CAB FAC#3270 (Conversion / Alteration) | B5: SF | C5: =BACKUP!B5 | D5: =BACKUP!B11 | E5: =ROUND(C5*D5/1000,0)
A7: Subtotal | E7: =BACKUP!B13
A8: Contingency (10.0%) | E8: =ROUND(BACKUP!B17/1000,0)
A9: Total Contract Cost | E9: =ROUND(BACKUP!B18/1000,0)
A10: Supervision, Inspection and Overhead (8.0%) | E10: =ROUND(BACKUP!B19/1000,0)
A11: Total Funded Cost | E11: =ROUND(BACKUP!B20/1000,0)
A12: Design-Build - Design Cost (4.0%) | E12: =ROUND(BACKUP!B21/1000,0)
A13: TOTAL PROJECT COST | E13: =BACKUP!B23
A14: Planning and Design (6.0%) (NON ADD) | E14: =ROUND(BACKUP!B24/1000,0)
A15: Equipment from Other Appropriations (NON ADD) | E15: 0
A17: Classification of Work
A18: Construction | E18: =E13
A19: Special Interest Codes
A20: Restoration and Modernization | E20: =E13

Sheet BLOCK10
A1: 10. Description of Proposed Construction
A3: The building serves as the primary automotive organizational shop for 4th Marine Regiment (4th MarRegt) and Combat Logistics Battalion 4 (CLB-4) on Camp Schwab. Following completion of this project, the building will remain in operational use for a minimum of 20 years. This project provides for the repair by replacement of the facility's failing mechanical, electrical, and life safety systems, correction of moisture-related architectural deficiencies, modernization of the telecommunications infrastructure, and installation of a mass notification system across both floors to meet current operational requirements, network standards, and UFC compliance. Minor deficiencies identified during the project scope will also be repaired. The project also replaces end-of-life exhaust systems, repairs plumbing safety stations, and addresses exterior door serviceability. MECHANICAL: The project will replace all seven existing HVAC split unit systems and 24 associated indoor fan coil units throughout the facility. New split unit HVAC will be installed in the first and second floor hallways. The air-exchange infrastructure will be redesigned to improve building-wide air circulation, including replacement of ventilation components, evaluation and right-sizing of fan power, and installation of door louvers. All four direct outdoor air supply units serving administrative areas will be replaced. Twenty-two exhaust fans serving restrooms, shops, mechanical rooms, and maintenance bays will be replaced. Ten vehicle exhaust hose reel assemblies in the maintenance bays will be replaced. The abandoned dust collection system in the Wood Shop will be fully removed. The welding exhaust system in the Welding Shop, including fans, roof ventilator, exhaust hood, and associated ductwork, will be repaired and restored. The battery room ventilation and conditioning system will be upgraded to meet code requirements. The compressed air system will be inspected, pressure-tested, and repaired as necessary. ELECTRICAL: All high-bay overhead lighting fixtures will be replaced throughout the facility, including 62 EA standard high-bay fixtures and 30 EA 400-watt metal halide fixtures requiring lift and rigging. All motion sensor-capable and optically- sensored lighting fixtures will be replaced. Electrical panel work, circuit modifications, and branch wiring associated with fixture replacement will be performed on both floors. ARCHITECTURAL: Replace mold/mildew-affected ceiling tile. Repair gypsum and concrete wall damage. Resecure exterior HVAC anchor cables. Remediate restroom mold/mildew. COMMUNICATIONS: New Category 6 infrastructure will be installed throughout the facility according to the current MCIPAC G-6 policy. Both telecom rooms are included in scope. Seventy NIPR network drops will be installed to support 4th Marine Regiment and CLB-4 operational requirements. CYBERSECURITY: The project's design and construction shall fully address Facility- Related Control Systems (FRCS) cybersecurity requirements, to include cybersecurity commissioning. These requirements are in accordance with current Department of Defense (DoD) criteria, Unified Facilities Criteria (UFC) standards, and National Institute of Standards and Technology (NIST) guidelines. Cybersecurity features include hardware, software, documentation, and testing provided by the construction contractor for FRCS. Cybersecurity commissioning covers government-provided documentation and testing for FRCS cybersecurity. PLUMBING: All emergency eyewash and shower stations will be replaced building-wide. Additional emergency shower capability will be added at maintenance bay locations currently served by eyewash only, in compliance with ANSI Z358.1 distance requirements. The second-floor electric water cooler will be replaced. LIFE SAFETY: Emergency lighting fixtures will be replaced with units incorporating integral battery backup throughout the facility. A mass notification system will be installed in compliance with applicable UFC guidelines and Fire Protection Engineering for Facilities.

Sheet BACKUP
A1: BACKUP - Locked TPC back-solver (drives BLOCK9 face)
A3: INPUTS (locked)
A4: Locked TPC ($) | B4: 3527753
A5: GSF (iNFADS, locked Quantity) | B5: 25390
A6: PRV ($, iNFADS) | B6: 39507617
A7: LSH ($, 2.5% of PRV) | B7: =B6*0.025
A8: Multiplier (1.10 x 1.08 x 1.04) | B8: 1.23552
A10: PAX ENTRY (what Anthony types into Block 9)
A11: Unit Cost ($/SF) | B11: =ROUND(B4/B5/B8,2)
A12: Items Table Subtotal (raw $) = GSF x UC | B12: =B5*B11
A13: Items Table Subtotal ($000) | B13: =ROUND(B12/1000,0)
A15: PAX ROLLUP (computed from items table subtotal)
A16: Subtotal ($) | B16: =B12
A17: Contingency (10.0%) | B17: =B16*0.10
A18: Total Contract Cost | B18: =B16+B17
A19: SIOH (8.0%) | B19: =B18*0.08
A20: Total Funded Cost | B20: =B18+B19
A21: Design-Build Design (4.0%) | B21: =B20*0.04
A22: Total Project Cost ($) | B22: =B20+B21
A23: Total Project Cost ($000) | B23: =ROUND(B22/1000,0)
A24: Planning and Design (6.0%) (NON ADD) | B24: =B22*0.06
A26: RECONCILIATION
A27: Workbook TPC ($) | B27: =B22
A28: Locked TPC ($) | B28: =B4
A29: Delta ($) | B29: =B27-B28
A30: Workbook TPC ($000) | B30: =B23
A31: Locked TPC ($000, printed) | B31: =ROUND(B4/1000,0)
A32: Delta ($000) - MUST BE 0 | B32: =B30-B31

Sheet RATES
A1: RATES (PAX Associated Costs and project parameters)
A3: PAX Associated Costs (pre-loaded by operator)
A4: Contingency | B4: 0.1 | C4: FSRM program-directed; CRB Guidelines May 2024 (REV #15)
A5: Supervision Inspection and Overhead (SIOH) | B5: 0.08 | C5: OCONUS FSRM customer-directed for MCIPAC G-F
A6: Design Build (DBD) - REQUIRED | B6: 0.04 | C6: UFC 3-730-01 (2024) - applied after Total Funded Cost
A7: Planning and Design (P&D) (NON ADD) | B7: 0.06 | C7: Does not roll into TPC
A9: Project parameters
A10: Area Cost Factor (ACF) | B10: 1.85 | C10: UFC 3-701-01 w/Change 7 (25 Jul 2025), Table 4-1, M67400-0004 OCONUS Okinawa
A11: LSH Rate (% of PRV) | B11: 0.025 | C11: Local direction at startup
A12: JPY/USD Planning Rate | B12: 150.4415 | C12: FY26 budget planning rate
A13: JPY/USD H.10 Rate (live) | C13: Verify Federal Reserve H.10 on date of PAX submission
A14: Escalation (annual) | B14: 0.021 | C14: OSD FY25 published rate
A15: General Requirements | B15: 0.1 | C15: FSRM program-directed

Sheet REFERENCES
A1: REFERENCES (authority cites)
A3: Document | B3: Date / Edition | C3: Authority for
A4: MCO 11000.5 | B4: 03 Jun 2016 | C4: Real Property FSRM Program
A5: MCO 11000.12 | B5: 08 Sep 2014 | C5: Real Property Facilities Manual
A6: CRB Guidelines (REV #15) | B6: May 2024 | C6: Block 9 line-item sequencing
A7: UFC 3-701-01 with Change 7 | B7: 25 Jul 2025 | C7: PUC and ACF tables, Equation 3-1 PRV formula
A8: UFC 3-730-01 | B8: 2024 | C8: Design-Build contracting; DB Design 4% applied after TFC
A9: JED Cost Estimating Guide | B9: Nov 2025 | C9: Cost estimating methodology
A10: Japan District Design Guide v9 | B10: April 2025 | C10: Okinawa-specific design criteria
A12: NOT CITED
A13: NAVFAC 11010.44E | B13: INACTIVE | C13: Inactivated by 1987 issuance; not citable
